analysis_engine/__init__.py
analysis_engine/ae_talib.py
analysis_engine/algo.py
analysis_engine/algo_runner.py
analysis_engine/api_requests.py
analysis_engine/build_algo_request.py
analysis_engine/build_buy_order.py
analysis_engine/build_dataset_node.py
analysis_engine/build_df_from_redis.py
analysis_engine/build_entry_call_spread_details.py
analysis_engine/build_entry_put_spread_details.py
analysis_engine/build_exit_call_spread_details.py
analysis_engine/build_exit_put_spread_details.py
analysis_engine/build_option_spread_details.py
analysis_engine/build_publish_request.py
analysis_engine/build_result.py
analysis_engine/build_sell_order.py
analysis_engine/build_trade_history_entry.py
analysis_engine/charts.py
analysis_engine/compress_data.py
analysis_engine/consts.py
analysis_engine/convert_df_to_json.py
analysis_engine/dataset_scrub_utils.py
analysis_engine/dict_to_csv.py
analysis_engine/extract.py
analysis_engine/extract_utils.py
analysis_engine/fetch.py
analysis_engine/get_data_from_redis_key.py
analysis_engine/get_pricing.py
analysis_engine/get_task_results.py
analysis_engine/holidays.py
analysis_engine/load_algo_dataset_from_file.py
analysis_engine/load_algo_dataset_from_redis.py
analysis_engine/load_algo_dataset_from_s3.py
analysis_engine/load_dataset.py
analysis_engine/load_history_dataset.py
analysis_engine/load_history_dataset_from_file.py
analysis_engine/load_history_dataset_from_s3.py
analysis_engine/load_report_dataset_from_file.py
analysis_engine/options_dates.py
analysis_engine/plot_trading_history.py
analysis_engine/prepare_dict_for_algo.py
analysis_engine/prepare_history_dataset.py
analysis_engine/prepare_report_dataset.py
analysis_engine/publish.py
analysis_engine/restore_dataset.py
analysis_engine/run_algo.py
analysis_engine/run_custom_algo.py
analysis_engine/s3_read_contents_from_key.py
analysis_engine/send_to_slack.py
analysis_engine/set_data_in_redis_key.py
analysis_engine/show_dataset.py
analysis_engine/start_worker.py
stock_analysis_engine-1.9.15.dist-info/LICENSE
stock_analysis_engine-1.9.15.dist-info/METADATA
stock_analysis_engine-1.9.15.dist-info/WHEEL
stock_analysis_engine-1.9.15.dist-info/entry_points.txt
stock_analysis_engine-1.9.15.dist-info/top_level.txt
stock_analysis_engine-1.9.15.dist-info/RECORD
