Metadata-Version: 2.1
Name: stock-analysis-engine
Version: 1.9.15
Summary: Backtest 1000s of minute-by-minute trading algorithms. Automated pricing data ingestion from: IEX Cloud (https://iexcloud.io), Tradier (https://tradier.com) and FinViz. Datasets and trading performance automatically compressed and published to S3 for building AI training datasets for teaching DNNs how to trade. Runs on Kubernetes with Helm and docker-compose. >150 million trading history rows generated from +5000 algorithms
Home-page: https://github.com/AlgoTraders/stock-analysis-engine
Author: Jay Johnson
Author-email: jay.p.h.johnson@gmail.com
License: UNKNOWN
Platform: UNKNOWN
Classifier: Development Status :: 5 - Production/Stable
Classifier: Intended Audience :: Developers
Classifier: License :: OSI Approved :: Apache Software License
Classifier: Operating System :: OS Independent
Classifier: Programming Language :: Python :: 3.6
Classifier: Programming Language :: Python :: Implementation :: PyPy
Classifier: Topic :: Software Development :: Libraries :: Python Modules
Requires-Dist: boto3
Requires-Dist: bs4
Requires-Dist: celery
Requires-Dist: celery[redis]
Requires-Dist: colorlog
Requires-Dist: coverage
Requires-Dist: flake8
Requires-Dist: future
Requires-Dist: matplotlib
Requires-Dist: mock
Requires-Dist: numpy
Requires-Dist: pandas
Requires-Dist: pep8
Requires-Dist: pycodestyle
Requires-Dist: pylint
Requires-Dist: recommonmark
Requires-Dist: redis (>=3.2.0)
Requires-Dist: seaborn
Requires-Dist: sphinx
Requires-Dist: sphinx-autobuild
Requires-Dist: sphinx-rtd-theme
Requires-Dist: spylunking
Requires-Dist: tabulate
Requires-Dist: trading-calendars
Requires-Dist: unittest2
Requires-Dist: urllib3
Requires-Dist: ujson
Requires-Dist: vprof
Requires-Dist: awscli
Requires-Dist: h5py
Requires-Dist: keras
Requires-Dist: scikit-learn
Requires-Dist: tables
Requires-Dist: ta-lib
Requires-Dist: tensorflow
